__init__.py
mozlib.py
mozlib-1.0.0.dist-info/LICENSE
mozlib-1.0.0.dist-info/METADATA
mozlib-1.0.0.dist-info/WHEEL
mozlib-1.0.0.dist-info/top_level.txt
mozlib-1.0.0.dist-info/RECORD
